odoo10_addon_web_widget_darkroom-10.0.1.0.0-py2.7-nspkg.pth
odoo/addons/web_widget_darkroom/README.rst
odoo/addons/web_widget_darkroom/__init__.py
odoo/addons/web_widget_darkroom/__manifest__.py
odoo/addons/web_widget_darkroom/static/description/icon.png
odoo/addons/web_widget_darkroom/static/description/modal_screenshot_1.png
odoo/addons/web_widget_darkroom/static/description/modal_screenshot_2.png
odoo/addons/web_widget_darkroom/static/lib/darkroomjs/core/darkroom.js
odoo/addons/web_widget_darkroom/static/lib/darkroomjs/core/plugin.js
odoo/addons/web_widget_darkroom/static/lib/darkroomjs/core/transformation.js
odoo/addons/web_widget_darkroom/static/lib/darkroomjs/core/utils.js
odoo/addons/web_widget_darkroom/static/lib/js/fabric.js
odoo/addons/web_widget_darkroom/static/src/js/widget_darkroom.js
odoo/addons/web_widget_darkroom/static/src/js/widget_darkroom_modal.js
odoo/addons/web_widget_darkroom/static/src/js/plugins/darkroom.crop.js
odoo/addons/web_widget_darkroom/static/src/js/plugins/darkroom.history.js
odoo/addons/web_widget_darkroom/static/src/js/plugins/darkroom.rotate.js
odoo/addons/web_widget_darkroom/static/src/js/plugins/darkroom.zoom.js
odoo/addons/web_widget_darkroom/static/src/less/darkroom.less
odoo/addons/web_widget_darkroom/static/src/xml/field_templates.xml
odoo/addons/web_widget_darkroom/tests/__init__.py
odoo/addons/web_widget_darkroom/tests/test_darkroom_modal.py
odoo/addons/web_widget_darkroom/views/assets.xml
odoo/addons/web_widget_darkroom/wizards/__init__.py
odoo/addons/web_widget_darkroom/wizards/darkroom_modal.py
odoo/addons/web_widget_darkroom/wizards/darkroom_modal.xml
odoo10_addon_web_widget_darkroom-10.0.1.0.0.dist-info/DESCRIPTION.rst
odoo10_addon_web_widget_darkroom-10.0.1.0.0.dist-info/METADATA
odoo10_addon_web_widget_darkroom-10.0.1.0.0.dist-info/RECORD
odoo10_addon_web_widget_darkroom-10.0.1.0.0.dist-info/WHEEL
odoo10_addon_web_widget_darkroom-10.0.1.0.0.dist-info/metadata.json
odoo10_addon_web_widget_darkroom-10.0.1.0.0.dist-info/namespace_packages.txt
odoo10_addon_web_widget_darkroom-10.0.1.0.0.dist-info/top_level.txt
